benford_law/__init__.py
benford_law/benford_law.py
benford_law-0.1.2.dist-info/LICENSE
benford_law-0.1.2.dist-info/METADATA
benford_law-0.1.2.dist-info/WHEEL
benford_law-0.1.2.dist-info/top_level.txt
benford_law-0.1.2.dist-info/RECORD
