Metadata-Version: 2.1
Name: benford-law
Version: 0.1.2
Summary: A python tool to calculate the Benford´s Law from a dataset or image
Home-page: https://github.com/rafaelmata357/benford
Author: Rafael Mata
Author-email: rafaelmata357@gmail.com
License: UNKNOWN
Platform: UNKNOWN
Classifier: Programming Language :: Python :: 3
Classifier: License :: OSI Approved :: MIT License
Classifier: Operating System :: OS Independent
Requires-Python: >=3.6
